client/__init__.py
client/decorators.py
client/descriptors.py
client/err.py
client/metaclasses.py
client/client/__init__.py
client/client/add_contact.py
client/client/database.py
client/client/del_contact.py
client/client/main_window.py
client/client/main_window_conv.py
client/client/start_dialog.py
client/client/transport.py
client/common/__init__.py
client/common/utils.py
client/common/variables.py
client/documents/__init__.py
client/documents/source/__init__.py
client/documents/source/conf.py
client/log/__init__.py
client/log/client_log_config.py
client/log/server_log_config.py
client/tests/__init__.py
client/tests/test_client.py
client/tests/test_server.py
client/tests/test_utils.py
my_first_messager_client-0.0.1.dist-info/METADATA
my_first_messager_client-0.0.1.dist-info/WHEEL
my_first_messager_client-0.0.1.dist-info/top_level.txt
my_first_messager_client-0.0.1.dist-info/RECORD
